[
  {
    "id": "quote-001",
    "character_name": "Eren Yeager",
    "quote_text": "If you win, you live. If you lose, you die. If you don't fight, you can't win!",
    "episode_reference": "S1E5",
    "vibe_tags": ["motivational", "battle"]
  },
  {
    "id": "quote-002",
    "character_name": "Armin Arlert",
    "quote_text": "Someone who can't sacrifice anything, can't change anything.",
    "episode_reference": "S1E24",
    "vibe_tags": ["tactical", "strategic"]
  },
  {
    "id": "quote-003",
    "character_name": "Levi Ackerman",
    "quote_text": "The only thing we're allowed to do is believe that we won't regret the choice we made.",
    "episode_reference": "S1E19",
    "vibe_tags": ["stoic", "motivational"]
  },
  {
    "id": "quote-004",
    "character_name": "Mikasa Ackerman",
    "quote_text": "This world is cruel, but it is also very beautiful.",
    "episode_reference": "S1E6",
    "vibe_tags": ["reflective", "emotional"]
  }
]
